scikit_autoeval-1.1.0.dist-info/licenses/LICENSE
skeval/base.py
skeval/utils.py
skeval/evaluators/__init__.py
skeval/evaluators/agreement.py
skeval/evaluators/confidence.py
skeval/evaluators/regression.py
skeval/evaluators/regression_noise.py
skeval/evaluators/shap.py
skeval/evaluators/tests/test_agreement.py
skeval/evaluators/tests/test_confidence.py
skeval/evaluators/tests/test_regression.py
skeval/evaluators/tests/test_regression_noise.py
skeval/evaluators/tests/test_shap.py
skeval/examples/agreement_example.py
skeval/examples/confidence_example.py
skeval/examples/regression_example.py
skeval/examples/regression_noise_example.py
skeval/examples/score_error_example.py
skeval/examples/shap_example.py
skeval/metrics/__init__.py
skeval/metrics/comparison.py
skeval/metrics/scorers.py
skeval/metrics/tests/test_comparison.py
skeval/metrics/tests/test_scorers.py
skeval/plots/graphics_exemple.py
skeval/tests/test_base.py
skeval/tests/test_utils.py
scikit_autoeval-1.1.0.dist-info/METADATA
scikit_autoeval-1.1.0.dist-info/WHEEL
scikit_autoeval-1.1.0.dist-info/top_level.txt
scikit_autoeval-1.1.0.dist-info/RECORD
