Metadata-Version: 2.4
Name: scikit-autoeval
Version: 1.1.0
Summary: Open-source AutoEval library for automatic evaluation of supervised machine learning models.
Author-email: Lucas Santos Rodrigues <lucasantos2003@gmail.com>, Ismael Santana Silva <ismaelsantana@cefetmg.br>
License: BSD-3-Clause
Project-URL: Homepage, https://github.com/scikit-autoeval/scikit-autoeval
Project-URL: Documentation, https://scikit-autoeval.github.io/scikit-autoeval/
Project-URL: Source, https://github.com/scikit-autoeval/scikit-autoeval
Keywords: machine learning,automated evaluation,model evaluation,AutoEval,ML metrics,scikit-learn,python
Classifier: Development Status :: 4 - Beta
Classifier: Intended Audience :: Science/Research
Classifier: Intended Audience :: Developers
Classifier: License :: OSI Approved :: BSD License
Classifier: Programming Language :: Python
Classifier: Programming Language :: Python :: 3
Classifier: Programming Language :: Python :: 3.8
Classifier: Programming Language :: Python :: 3.9
Classifier: Programming Language :: Python :: 3.10
Classifier: Programming Language :: Python :: 3.11
Classifier: Topic :: Scientific/Engineering :: Artificial Intelligence
Classifier: Topic :: Software Development :: Libraries
Requires-Python: >=3.8
License-File: LICENSE
Requires-Dist: scikit-learn>=1.0
Requires-Dist: numpy
Requires-Dist: pandas
Requires-Dist: matplotlib
Requires-Dist: shap
Requires-Dist: xgboost
Dynamic: license-file
